setup.py
odoo/addons/delivery_somconnexio/CHANGELOG.md
odoo/addons/delivery_somconnexio/README.rst
odoo/addons/delivery_somconnexio/__init__.py
odoo/addons/delivery_somconnexio/__manifest__.py
odoo/addons/delivery_somconnexio/controllers/__init__.py
odoo/addons/delivery_somconnexio/controllers/user_contoller.py
odoo/addons/delivery_somconnexio/crons/crm_track_correos_delivery_cron.xml
odoo/addons/delivery_somconnexio/data/crm_stage_data.xml
odoo/addons/delivery_somconnexio/i18n/ca_ES.po
odoo/addons/delivery_somconnexio/i18n/es.po
odoo/addons/delivery_somconnexio/listeners/__init__.py
odoo/addons/delivery_somconnexio/listeners/crm_lead_listener.py
odoo/addons/delivery_somconnexio/models/__init__.py
odoo/addons/delivery_somconnexio/models/crm_lead.py
odoo/addons/delivery_somconnexio/security/ir.model.access.csv
odoo/addons/delivery_somconnexio/tests/__init__.py
odoo/addons/delivery_somconnexio/tests/listeners/__init__.py
odoo/addons/delivery_somconnexio/tests/listeners/test_crm_lead_listener.py
odoo/addons/delivery_somconnexio/tests/models/__init__.py
odoo/addons/delivery_somconnexio/tests/models/test_crm_lead.py
odoo/addons/delivery_somconnexio/tests/wizards/__init__.py
odoo/addons/delivery_somconnexio/tests/wizards/test_crm_lead_generate_SIM_delivery_wizard.py
odoo/addons/delivery_somconnexio/views/crm_lead.xml
odoo/addons/delivery_somconnexio/wizards/__init__.py
odoo/addons/delivery_somconnexio/wizards/crm_lead_generate_SIM_delivery/__init__.py
odoo/addons/delivery_somconnexio/wizards/crm_lead_generate_SIM_delivery/crm_lead_generate_SIM_delivery.py
odoo/addons/delivery_somconnexio/wizards/crm_lead_generate_SIM_delivery/crm_lead_generate_SIM_delivery.xml
odoo/addons/delivery_somconnexio/wizards/crm_lead_print_SIM_delivery_label/__init__.py
odoo/addons/delivery_somconnexio/wizards/crm_lead_print_SIM_delivery_label/crm_lead_print_SIM_delivery_label.py
odoo/addons/delivery_somconnexio/wizards/crm_lead_print_SIM_delivery_label/crm_lead_print_SIM_delivery_label.xml
odoo_addon_delivery_somconnexio.egg-info/PKG-INFO
odoo_addon_delivery_somconnexio.egg-info/SOURCES.txt
odoo_addon_delivery_somconnexio.egg-info/dependency_links.txt
odoo_addon_delivery_somconnexio.egg-info/not-zip-safe
odoo_addon_delivery_somconnexio.egg-info/requires.txt
odoo_addon_delivery_somconnexio.egg-info/top_level.txt